{
  "type": "Feature",
  "properties": {
    "iso:country":"BH",
    "name:ara_x_preferred":[
        "\u0627\u064e\u0644\u0631\u064f\u0651\u0645\u064e\u064a\u0652\u062b\u064e\u0629"
    ],
    "name:unk_x_variant":[
        "Al-Rumayth\u0101\u2019"
    ],
    "qs:gn_country":"BH",
    "qs:gn_fcode":"PPL",
    "qs:gn_pop":0,
    "qs:name":"Ar Rumaythah",
    "qs:name_adm0":"\u0627\u0644\u0628\u062d\u0631\u064a\u0646",
    "qs:name_adm1":"\u0627\u0644\u062c\u0646\u0648\u0628\u064a\u0629",
    "qs:photos":7,
    "qs:photos_1k":1,
    "qs:photos_9k":1,
    "qs:photos_9r":1,
    "qs:photos_all":7,
    "qs:photos_sr":1,
    "qs:placetype":"Town",
    "qs:pop_sr":"0",
    "qs:woe_adm0":23424753,
    "wof:name":"Ar Rumaythah",
    "wof:placetype":"locality"
},
  "geometry": {"coordinates":[50.55306,25.92389],"type":"Point"}
}