{
  "type": "Feature",
  "properties": {
    "iso:country":"BH",
    "name:eng_x_preferred":[
        "Halat Naim-block 248"
    ],
    "qs:gn_local":0,
    "qs:local_max":441,
    "qs:local_sum":1029,
    "qs:localhoods":10,
    "qs:name":"Halat Naim-block 248",
    "qs:name_adm0":"\u0627\u0644\u0628\u062d\u0631\u064a\u0646",
    "qs:name_adm1":"\u0627\u0644\u0645\u062d\u0631\u0642",
    "qs:name_adm2":"\u062d\u0627\u0644\u0629 \u0627\u0644\u0633\u0644\u0637\u0629",
    "qs:name_local":"\u0627\u0644\u0645\u062d\u0631\u0642",
    "qs:photo_max":10,
    "qs:photo_sum":48,
    "qs:placetype":"Suburb",
    "qs:quad_count":9,
    "qs:woe_adm0":23424753,
    "qs:woe_adm1":2344724,
    "qs:woe_adm2":56438100,
    "qs:woe_lau":0,
    "qs:woe_local":1967059,
    "qs:woe_ver":"7.10.0",
    "wof:lang":[
        "eng"
    ],
    "wof:name":"Halat Naim-block 248",
    "wof:placetype":"neighbourhood"
},
  "geometry": {"coordinates":[50.627833,26.227066],"type":"Point"}
}