{
  "type": "Feature",
  "properties": {
    "gn:admin1_code":"17",
    "gn:asciiname":"`Askar",
    "gn:country_code":"BH",
    "gn:dem":8,
    "gn:feature_class":"P",
    "gn:feature_code":"PPL",
    "gn:name":"\u2018Askar",
    "gn:population":0,
    "gn:timezone":"Asia/Bahrain",
    "iso:country":"BH",
    "name:ara_x_preferred":[
        "\u0639\u064e\u0633\u0652\u0643\u064e\u0631"
    ],
    "name:und_x_variant":[
        "Al \u2018Askar",
        "\u2018Askar"
    ],
    "wof:name":"`Askar",
    "wof:placetype":"locality"
},
  "geometry": {"coordinates":[50.61639,26.05722],"type":"Point"}
}