{
  "type": "Feature",
  "properties": {
    "iso:country":"BH",
    "qs:gn_pop":0,
    "qs:name":"\u0645\u062f\u064a\u0646\u0629 \u0639\u064a\u0633\u0649",
    "qs:name_adm0":"\u0627\u0644\u0628\u062d\u0631\u064a\u0646",
    "qs:name_adm1":"\u0627\u0644\u0648\u0633\u0637\u0649",
    "qs:photos":11,
    "qs:photos_1k":2,
    "qs:photos_9k":1,
    "qs:photos_9r":4,
    "qs:photos_all":153,
    "qs:photos_sr":1,
    "qs:placetype":"Town",
    "qs:pop_sr":"0",
    "qs:woe_adm0":23424753,
    "wof:name":"\u0645\u062f\u064a\u0646\u0629 \u0639\u064a\u0633\u0649",
    "wof:placetype":"locality"
},
  "geometry": {"coordinates":[50.556968,26.169612],"type":"Point"}
}