{
  "type": "Feature",
  "properties": {
    "iso:country":"BH",
    "name:ara_x_preferred":[
        "\u0645\u062c\u0645\u0639 351"
    ],
    "name:eng_x_preferred":[
        "Block 351"
    ],
    "name:eng_x_variant":[
        "Block 351"
    ],
    "name:unk_x_variant":[
        "\u0645\u062c\u0645\u0639 351"
    ],
    "qs:gn_adm0_cc":"BH",
    "qs:gn_local":290340,
    "qs:local_max":1563,
    "qs:local_sum":7156,
    "qs:localhoods":22,
    "qs:name":"\u0645\u062c\u0645\u0639 351",
    "qs:name_adm0":"\u0627\u0644\u0628\u062d\u0631\u064a\u0646",
    "qs:name_adm1":"\u0627\u0644\u0645\u0646\u0627\u0645\u0629",
    "qs:name_adm2":"\u0627\u0644\u0635\u0648\u064a\u0641\u064a\u0629",
    "qs:name_en":"Block 351",
    "qs:name_local":"\u0627\u0644\u0645\u0646\u0627\u0645\u0629",
    "qs:photo_max":81,
    "qs:photo_sum":361,
    "qs:placetype":"Suburb",
    "qs:quad_count":22,
    "qs:woe_adm0":23424753,
    "qs:woe_adm1":2344720,
    "qs:woe_adm2":56438073,
    "qs:woe_lau":0,
    "qs:woe_local":1967057,
    "qs:woe_ver":"7.10.0",
    "wof:lang":[
        "ara"
    ],
    "wof:name":"\u0645\u062c\u0645\u0639 351",
    "wof:placetype":"neighbourhood"
},
  "geometry": {"coordinates":[50.558618,26.231757],"type":"Point"}
}