{
  "type": "Feature",
  "properties": {
    "iso:country":"BH",
    "name:eng_x_preferred":[
        "Muharraq City-block 211"
    ],
    "qs:gn_local":0,
    "qs:local_max":441,
    "qs:local_sum":1029,
    "qs:localhoods":10,
    "qs:name":"Muharraq City-block 211",
    "qs:name_adm0":"\u0627\u0644\u0628\u062d\u0631\u064a\u0646",
    "qs:name_adm1":"\u0627\u0644\u0645\u062d\u0631\u0642",
    "qs:name_adm2":"\u0627\u0644\u0645\u062d\u0631\u0642",
    "qs:name_local":"\u0627\u0644\u0645\u062d\u0631\u0642",
    "qs:photo_max":214,
    "qs:photo_sum":441,
    "qs:placetype":"Suburb",
    "qs:quad_count":12,
    "qs:woe_adm0":23424753,
    "qs:woe_adm1":2344724,
    "qs:woe_adm2":56438041,
    "qs:woe_lau":0,
    "qs:woe_local":1967059,
    "qs:woe_ver":"7.10.0",
    "wof:lang":[
        "eng"
    ],
    "wof:name":"Muharraq City-block 211",
    "wof:placetype":"neighbourhood"
},
  "geometry": {"coordinates":[50.611582,26.249291],"type":"Point"}
}