{
  "type": "Feature",
  "properties": {
    "gn:admin1_code":"18",
    "gn:asciiname":"Jabalat Habashi",
    "gn:country_code":"BH",
    "gn:dem":9,
    "gn:feature_class":"P",
    "gn:feature_code":"PPL",
    "gn:name":"Jabalat \u1e28abash\u012b",
    "gn:population":0,
    "gn:timezone":"Asia/Bahrain",
    "iso:country":"BH",
    "name:ara_x_preferred":[
        "\u062c\u064e\u0628\u064e\u0644\u064e\u0629 \u062d\u064e\u0628\u064e\u0634\u0650\u064a"
    ],
    "name:und_x_variant":[
        "Jabalat Habshi",
        "Jabalat \u1e28abash\u012b"
    ],
    "wof:name":"Jabalat Habashi",
    "wof:placetype":"locality"
},
  "geometry": {"coordinates":[50.5275,26.21722],"type":"Point"}
}