{
  "type": "Feature",
  "properties": {
    "iso:country":"BH",
    "name:eng_x_preferred":[
        "Barbar-block 528"
    ],
    "qs:gn_adm0_cc":"BH",
    "qs:gn_local":290286,
    "qs:gn_nam_loc":"al mashrab",
    "qs:gn_namadm1":"19",
    "qs:local_max":108,
    "qs:local_sum":108,
    "qs:localhoods":1,
    "qs:name":"Barbar-block 528",
    "qs:name_adm0":"\u0627\u0644\u0628\u062d\u0631\u064a\u0646",
    "qs:name_adm1":"\u0627\u0644\u0634\u0645\u0627\u0644\u064a\u0629",
    "qs:name_adm2":"\u0628\u0627\u0631\u0628\u0627\u0631",
    "qs:name_local":"\u0628\u0627\u0631\u0628\u0627\u0631",
    "qs:photo_max":102,
    "qs:photo_sum":108,
    "qs:placetype":"Suburb",
    "qs:quad_count":4,
    "qs:woe_adm0":23424753,
    "qs:woe_adm1":56051603,
    "qs:woe_adm2":56438058,
    "qs:woe_lau":0,
    "qs:woe_local":1966997,
    "qs:woe_ver":"7.10.0",
    "wof:lang":[
        "eng"
    ],
    "wof:name":"Barbar-block 528",
    "wof:placetype":"neighbourhood"
},
  "geometry": {"coordinates":[50.469894,26.225611],"type":"Point"}
}