{
  "type": "Feature",
  "properties": {
    "gn:admin1_code":"17",
    "gn:asciiname":"Oil City",
    "gn:country_code":"BH",
    "gn:dem":55,
    "gn:feature_class":"P",
    "gn:feature_code":"PPL",
    "gn:name":"Oil City",
    "gn:population":0,
    "gn:timezone":"Asia/Bahrain",
    "iso:country":"BH",
    "name:ara_x_preferred":[
        "\u0639\u064e\u0648\u064e\u0627\u0644\u0650\u064a"
    ],
    "name:ara_x_variant":[
        "\u2018Aw\u0101l\u012b"
    ],
    "name:und_x_variant":[
        "Al \u2018Aw\u0101l\u012b",
        "Bapco",
        "Al Chirabia",
        "Kirabad",
        "Al Ghiraibat"
    ],
    "wof:name":"Oil City",
    "wof:placetype":"locality"
},
  "geometry": {"coordinates":[50.55056,26.08444],"type":"Point"}
}