{
  "type": "Feature",
  "properties": {
    "gn:admin1_code":"17",
    "gn:asciiname":"Oil City",
    "gn:country_code":"BH",
    "gn:dem":55,
    "gn:feature_class":"P",
    "gn:feature_code":"PPL",
    "gn:name":"Oil City",
    "gn:population":0,
    "gn:timezone":"Asia/Bahrain",
    "iso:country":"BH",
    "name:ara_x_preferred":[
        "\u0639\u064e\u0648\u064e\u0627\u0644\u0650\u064a"
    ],
    "name:ara_x_variant":[
        "\u2018Aw\u0101l\u012b"
    ],
    "name:ceb_x_preferred":[
        "Oil City"
    ],
    "name:deu_x_preferred":[
        "Oil City"
    ],
    "name:est_x_preferred":[
        "Oil City"
    ],
    "name:fra_x_preferred":[
        "Oil City"
    ],
    "name:ita_x_preferred":[
        "Oil City"
    ],
    "name:nld_x_preferred":[
        "Oil City"
    ],
    "name:pol_x_preferred":[
        "Oil City"
    ],
    "name:por_x_preferred":[
        "Oil City"
    ],
    "name:rus_x_preferred":[
        "\u041e\u0439\u043b-\u0421\u0438\u0442\u0438"
    ],
    "name:spa_x_preferred":[
        "Oil City"
    ],
    "name:srp_x_preferred":[
        "\u041e\u0458\u043b \u0421\u0438\u0442\u0438"
    ],
    "name:und_x_variant":[
        "Al \u2018Aw\u0101l\u012b",
        "Bapco",
        "Al Chirabia",
        "Kirabad",
        "Al Ghiraibat"
    ],
    "name:urd_x_preferred":[
        "\u0622\u0626\u0644 \u0633\u0679\u06cc"
    ],
    "name:vol_x_preferred":[
        "Oil City"
    ],
    "wof:name":"Oil City",
    "wof:placetype":"locality"
},
  "geometry": {"coordinates":[50.55056,26.08444],"type":"Point"}
}