{
  "type": "Feature",
  "properties": {
    "iso:country":"BH",
    "name:ara_x_preferred":[
        "\u0645\u062c\u0645\u0639 304"
    ],
    "name:eng_x_preferred":[
        "Block 304"
    ],
    "name:eng_x_variant":[
        "Block 304"
    ],
    "qs:gn_adm0_cc":"BH",
    "qs:gn_local":290340,
    "qs:local_max":1563,
    "qs:local_sum":7156,
    "qs:localhoods":22,
    "qs:name":"\u0645\u062c\u0645\u0639 304",
    "qs:name_adm0":"\u0627\u0644\u0628\u062d\u0631\u064a\u0646",
    "qs:name_adm1":"\u0627\u0644\u0645\u0646\u0627\u0645\u0629",
    "qs:name_adm2":"\u0627\u0644\u0633\u0648\u0642",
    "qs:name_en":"Block 304",
    "qs:name_local":"\u0627\u0644\u0645\u0646\u0627\u0645\u0629",
    "qs:photo_max":103,
    "qs:photo_sum":438,
    "qs:placetype":"Suburb",
    "qs:quad_count":12,
    "qs:woe_adm0":23424753,
    "qs:woe_adm1":2344720,
    "qs:woe_adm2":56438103,
    "qs:woe_lau":0,
    "qs:woe_local":1967057,
    "qs:woe_ver":"7.10.0",
    "wof:lang":[
        "ara"
    ],
    "wof:name":"\u0645\u062c\u0645\u0639 304",
    "wof:placetype":"neighbourhood"
},
  "geometry": {"coordinates":[50.57444,26.235017],"type":"Point"}
}