{
  "type": "Feature",
  "properties": {
    "gn:admin1_code":"16",
    "gn:asciiname":"Marquban",
    "gn:country_code":"BH",
    "gn:dem":4,
    "gn:feature_class":"P",
    "gn:feature_code":"PPL",
    "gn:name":"Marq\u016bb\u0101n",
    "gn:population":0,
    "gn:timezone":"Asia/Bahrain",
    "iso:country":"BH",
    "name:ara_x_preferred":[
        "\u0645\u064e\u0631\u0652\u0642\u064f\u0648\u0628\u064e\u0627\u0646"
    ],
    "name:ara_x_variant":[
        "\u0645\u0631\u0642\u0648\u0628\u0627\u0646"
    ],
    "name:nno_x_preferred":[
        "Marquban"
    ],
    "name:und_x_variant":[
        "Mark\u016bb\u0101n",
        "Marq\u016bb\u0101n"
    ],
    "wof:name":"Marquban",
    "wof:placetype":"locality"
},
  "geometry": {"coordinates":[50.61833,26.16417],"type":"Point"}
}