{
  "type": "Feature",
  "properties": {
    "gn:admin1_code":"18",
    "gn:asciiname":"Maqaba",
    "gn:country_code":"BH",
    "gn:dem":10,
    "gn:feature_class":"P",
    "gn:feature_code":"PPL",
    "gn:name":"Maq\u0101b\u0101",
    "gn:population":0,
    "gn:timezone":"Asia/Bahrain",
    "iso:country":"BH",
    "name:ara_x_preferred":[
        "\u0645\u064e\u0642\u064e\u0627\u0628\u064e\u0627"
    ],
    "name:und_x_variant":[
        "Makaba",
        "Maq\u0101b\u0101"
    ],
    "wof:name":"Maqaba",
    "wof:placetype":"locality"
},
  "geometry": {"coordinates":[50.4875,26.21083],"type":"Point"}
}