{
  "type": "Feature",
  "properties": {
    "iso:country":"BH",
    "name:ara_x_preferred":[
        "\u0645\u062c\u0645\u0639 301"
    ],
    "name:eng_x_preferred":[
        "Block 301"
    ],
    "qs:gn_pop":0,
    "qs:name":"\u0645\u062c\u0645\u0639 301",
    "qs:name_adm0":"\u0627\u0644\u0628\u062d\u0631\u064a\u0646",
    "qs:name_adm1":"\u0627\u0644\u0645\u0646\u0627\u0645\u0629",
    "qs:photos":76,
    "qs:photos_1k":15,
    "qs:photos_9k":1,
    "qs:photos_9r":3,
    "qs:photos_all":76,
    "qs:photos_sr":3,
    "qs:placetype":"Suburb",
    "qs:pop_sr":"0",
    "qs:woe_adm0":23424753,
    "wof:name":"Block 301",
    "wof:placetype":"neighbourhood"
},
  "geometry": {"coordinates":[50.575561,26.229705],"type":"Point"}
}