{
  "type": "Feature",
  "properties": {
    "iso:country":"BH",
    "qs:gn_pop":0,
    "qs:name":"East Riffa-block 903",
    "qs:name_adm0":"\u0627\u0644\u0628\u062d\u0631\u064a\u0646",
    "qs:name_adm1":"\u0627\u0644\u062c\u0646\u0648\u0628\u064a\u0629",
    "qs:photos":25,
    "qs:photos_1k":5,
    "qs:photos_9k":1,
    "qs:photos_9r":1,
    "qs:photos_all":25,
    "qs:photos_sr":1,
    "qs:placetype":"Suburb",
    "qs:pop_sr":"0",
    "qs:woe_adm0":23424753,
    "wof:name":"East Riffa-block 903",
    "wof:placetype":"neighbourhood"
},
  "geometry": {"coordinates":[50.562515,26.117604],"type":"Point"}
}