{
  "type": "Feature",
  "properties": {
    "iso:country":"BH",
    "name:eng_x_preferred":[
        "Sanabis-block 408"
    ],
    "qs:gn_adm0_cc":"BH",
    "qs:gn_local":290215,
    "qs:gn_nam_loc":"jidd hafs",
    "qs:gn_namadm1":"16",
    "qs:local_max":424,
    "qs:local_sum":889,
    "qs:localhoods":5,
    "qs:name":"Sanabis-block 408",
    "qs:name_adm0":"\u0627\u0644\u0628\u062d\u0631\u064a\u0646",
    "qs:name_adm1":"\u0627\u0644\u0645\u0646\u0627\u0645\u0629",
    "qs:name_adm2":"\u0633\u0646\u0627\u0628\u0633",
    "qs:name_local":"\u062c\u062f \u062d\u0641\u0635",
    "qs:photo_max":26,
    "qs:photo_sum":118,
    "qs:placetype":"Suburb",
    "qs:quad_count":19,
    "qs:woe_adm0":23424753,
    "qs:woe_adm1":2344720,
    "qs:woe_adm2":56438024,
    "qs:woe_lau":0,
    "qs:woe_local":1967019,
    "qs:woe_ver":"7.10.0",
    "wof:lang":[
        "eng"
    ],
    "wof:name":"Sanabis-block 408",
    "wof:placetype":"neighbourhood"
},
  "geometry": {"coordinates":[50.550588,26.224902],"type":"Point"}
}