{
  "type": "Feature",
  "properties": {
    "iso:country":"BH",
    "name:eng_x_preferred":[
        "Budaiya-block 559"
    ],
    "qs:gn_local":0,
    "qs:local_max":2,
    "qs:local_sum":2,
    "qs:localhoods":1,
    "qs:name":"Budaiya-block 559",
    "qs:name_adm0":"\u0627\u0644\u0628\u062d\u0631\u064a\u0646",
    "qs:name_adm1":"\u0627\u0644\u0634\u0645\u0627\u0644\u064a\u0629",
    "qs:name_adm2":"\u0627\u0644\u0628\u062f\u064a\u0639",
    "qs:name_local":"\u0627\u0644\u0628\u062f\u064a\u0639",
    "qs:photo_max":1,
    "qs:photo_sum":2,
    "qs:placetype":"Suburb",
    "qs:quad_count":2,
    "qs:woe_adm0":23424753,
    "qs:woe_adm1":56051603,
    "qs:woe_adm2":56437977,
    "qs:woe_lau":0,
    "qs:woe_local":1967058,
    "qs:woe_ver":"7.10.0",
    "wof:lang":[
        "eng"
    ],
    "wof:name":"Budaiya-block 559",
    "wof:placetype":"neighbourhood"
},
  "geometry": {"coordinates":[50.443726,26.212128],"type":"Point"}
}